{
  "data_asset_type": null,
  "expectation_suite_name": "player_stats_suite",
  "expectations": [
    {
      "expectation_type": "expect_table_row_count_to_be_between",
      "kwargs": {
        "max_value": 10000000,
        "min_value": 1
      },
      "meta": {}
    },
    {
      "expectation_type": "expect_column_to_exist",
      "kwargs": {
        "column": "player_id"
      },
      "meta": {}
    },
    {
      "expectation_type": "expect_column_to_exist",
      "kwargs": {
        "column": "kd_ratio"
      },
      "meta": {}
    },
    {
      "expectation_type": "expect_column_to_exist",
      "kwargs": {
        "column": "acs"
      },
      "meta": {}
    },
    {
      "expectation_type": "expect_column_values_to_not_be_null",
      "kwargs": {
        "column": "player_id"
      },
      "meta": {}
    },
    {
      "expectation_type": "expect_column_values_to_be_unique",
      "kwargs": {
        "column": "player_id"
      },
      "meta": {}
    },
    {
      "expectation_type": "expect_column_values_to_be_between",
      "kwargs": {
        "column": "kd_ratio",
        "min_value": 0.0,
        "max_value": 10.0
      },
      "meta": {}
    },
    {
      "expectation_type": "expect_column_values_to_be_between",
      "kwargs": {
        "column": "acs",
        "min_value": 0.0,
        "max_value": 1000.0
      },
      "meta": {}
    },
    {
      "expectation_type": "expect_column_values_to_be_between",
      "kwargs": {
        "column": "headshot_pct",
        "min_value": 0.0,
        "max_value": 1.0
      },
      "meta": {}
    },
    {
      "expectation_type": "expect_column_values_to_be_of_type",
      "kwargs": {
        "column": "matches_played",
        "type_": "int"
      },
      "meta": {}
    },
    {
      "expectation_type": "expect_column_values_to_be_between",
      "kwargs": {
        "column": "matches_played",
        "min_value": 0,
        "max_value": 10000
      },
      "meta": {}
    },
    {
      "expectation_type": "expect_column_values_to_be_between",
      "kwargs": {
        "column": "win_rate",
        "min_value": 0.0,
        "max_value": 1.0
      },
      "meta": {}
    },
    {
      "expectation_type": "expect_column_values_to_not_be_null",
      "kwargs": {
        "column": "last_updated"
      },
      "meta": {}
    }
  ],
  "meta": {
    "citations": [
      {
        "citation_date": "2026-03-30",
        "comment": "Initial expectation suite for player_stats table"
      }
    ],
    "great_expectations_version": "0.18.0"
  }
}
